csvtotable/__init__.py
csvtotable/cli.py
csvtotable/convert.py
csvtotable/templates/template.j2
csvtotable/templates/js/dataTables.scroller.min.js
csvtotable/templates/js/jquery.dataTables.min.js
csvtotable/templates/js/jquery.min.js
excel2table/__init__.py
excel2table/cli.py
excel2table/convert.py
excel2table/templates/template.j2
excel2table/templates/js/buttons.chart.min.js
excel2table/templates/js/buttons.html5.min.js
excel2table/templates/js/buttons.kline.js
excel2table/templates/js/buttons.print.min.js
excel2table/templates/js/dataTables.buttons.js
excel2table/templates/js/dataTables.buttons.min.js
excel2table/templates/js/dataTables.scroller.min.js
excel2table/templates/js/echarts.min.js
excel2table/templates/js/jquery.dataTables.min.js
excel2table/templates/js/jquery.min.js
excel2table-2.2.1.dist-info/DESCRIPTION.rst
excel2table-2.2.1.dist-info/METADATA
excel2table-2.2.1.dist-info/RECORD
excel2table-2.2.1.dist-info/WHEEL
excel2table-2.2.1.dist-info/entry_points.txt
excel2table-2.2.1.dist-info/metadata.json
excel2table-2.2.1.dist-info/top_level.txt
